AfadLastQuakes/__init__.py
AfadLastQuakes/general.py
KandilliLastQuakes/__init__.py
KandilliLastQuakes/general.py
TurkeyLastQuakeAlert-0.2.0.dist-info/METADATA
TurkeyLastQuakeAlert-0.2.0.dist-info/WHEEL
TurkeyLastQuakeAlert-0.2.0.dist-info/notice.mp3
TurkeyLastQuakeAlert-0.2.0.dist-info/top_level.txt
TurkeyLastQuakeAlert-0.2.0.dist-info/RECORD
