Metadata-Version: 2.1
Name: TurkeyLastQuakeAlert
Version: 0.2.0
Summary: Kandilli and AFAD API.
Author: userdotcs
License: MIT
License-File: notice.mp3
